jsonloader/__init__.py
jsonloader/jsonloader.py
jsonloader/jsonloader2.py
jsonloader-0.9.1.dist-info/LICENSE
jsonloader-0.9.1.dist-info/METADATA
jsonloader-0.9.1.dist-info/WHEEL
jsonloader-0.9.1.dist-info/top_level.txt
jsonloader-0.9.1.dist-info/RECORD
