Metadata-Version: 2.1
Name: jsonloader
Version: 0.9.1
Summary: No more boilerplate to check and build a Python object from JSON.
Home-page: https://github.com/OhMajesticLama/jsonloader
Author-email: ohmajesticlama@gmail.com
Classifier: Programming Language :: Python :: 3
Classifier: Development Status :: 4 - Beta
Classifier: License :: OSI Approved :: MIT License
Classifier: Operating System :: OS Independent
Classifier: Environment :: Web Environment
Classifier: Intended Audience :: Developers
Classifier: Topic :: Software Development :: Libraries :: Python Modules
Requires-Python: >=3.8.10
License-File: LICENSE
Requires-Dist: typeguard (<4.0.0,>=3.0.1)
Provides-Extra: dev
Requires-Dist: pytest (>=7.0.1) ; extra == 'dev'
Requires-Dist: mypy (>=0.931) ; extra == 'dev'
Requires-Dist: coverage (>=6.3) ; extra == 'dev'
Requires-Dist: build (>=0.7.0) ; extra == 'dev'
Requires-Dist: ipython (>=8.0.1) ; extra == 'dev'
Requires-Dist: ipdb (>=0.13.9) ; extra == 'dev'
Requires-Dist: flake8 (>=4.0.1) ; extra == 'dev'
Requires-Dist: twine (>=3.8.0) ; extra == 'dev'
